{"features": [{"geometry": {"coordinates": [-74.00821007847789, 40.65599456301905], "type": "Point"}, "properties": {"address": "639 2 AVENUE"}, "type": "Feature"}, {"geometry": {"coordinates": [-74.0074136445214, 40.65659023457253], "type": "Point"}, "properties": {"address": "607 2 AVENUE"}, "type": "Feature"}, {"geometry": {"coordinates": [-74.00680460420898, 40.657114525339125], "type": "Point"}, "properties": {"address": "581 2 AVENUE"}, "type": "Feature"}, {"geometry": {"coordinates": [-74.00624961778047, 40.65764978904642], "type": "Point"}, "properties": {"address": "892 3 AVENUE"}, "type": "Feature"}, {"geometry": {"coordinates": [-74.00664230040884, 40.65593153427716], "type": "Point"}, "properties": {"address": "944 3 AVENUE"}, "type": "Feature"}, {"geometry": {"coordinates": [-74.00719006279007, 40.65540999292616], "type": "Point"}, "properties": {"address": "962 3 AVENUE"}, "type": "Feature"}, {"geometry": {"coordinates": [-74.00563335605929, 40.658242693446326], "type": "Point"}, "properties": {"address": "882 3 AVENUE"}, "type": "Feature"}, {"geometry": {"coordinates": [-74.00795061596658, 40.6562525906593], "type": "Point"}, "properties": {"address": "627 2 AVENUE"}, "type": "Feature"}], "properties": {"square footage": "3,350,373"}, "type": "FeatureCollection"}