{"features": [{"geometry": {"coordinates": [-73.96776849999999, 40.7600535], "type": "Point"}, "properties": {"address": "944 3 AVENUE"}, "type": "Feature"}, {"geometry": {"coordinates": [-73.9757807, 40.7454277], "type": "Point"}, "properties": {"address": "639 2 AVENUE"}, "type": "Feature"}, {"geometry": {"coordinates": [-73.97598049999999, 40.7451337], "type": "Point"}, "properties": {"address": "627 2 AVENUE"}, "type": "Feature"}, {"geometry": {"coordinates": [-73.9692714, 40.7579462], "type": "Point"}, "properties": {"address": "892 3 AVENUE"}, "type": "Feature"}, {"geometry": {"coordinates": [-73.96748339999999, 40.7607635], "type": "Point"}, "properties": {"address": "962 3 AVENUE"}, "type": "Feature"}, {"geometry": {"coordinates": [-73.9771706, 40.7435137], "type": "Point"}, "properties": {"address": "581 2 AVENUE"}, "type": "Feature"}, {"geometry": {"coordinates": [-73.9764532, 40.7443999], "type": "Point"}, "properties": {"address": "607 2 AVENUE"}, "type": "Feature"}, {"geometry": {"coordinates": [-73.9692714, 40.7579462], "type": "Point"}, "properties": {"address": "882 3 AVENUE"}, "type": "Feature"}], "properties": {"square footage": "3,350,373"}, "type": "FeatureCollection"}