{"features": [{"geometry": {"coordinates": [-73.97310053873714, 40.581163186421534], "type": "Point"}, "properties": {"address": "2790 WEST 5 STREET"}, "type": "Feature"}, {"geometry": {"coordinates": [-73.96979582853557, 40.580893374516876], "type": "Point"}, "properties": {"address": "2830 OCEAN PARKWAY"}, "type": "Feature"}], "properties": {"square footage": "3,059,938"}, "type": "FeatureCollection"}