{"features": [{"geometry": {"coordinates": [-74.00072912149855, 40.756524571019376], "type": "Point"}, "properties": {"address": "418 11 AVENUE"}, "type": "Feature"}, {"geometry": {"coordinates": [-74.00229569905618, 40.757951817751106], "type": "Point"}, "properties": {"address": "360 WEST STREET"}, "type": "Feature"}, {"geometry": {"coordinates": [-74.00109012812125, 40.75990883803094], "type": "Point"}, "properties": {"address": "608 WEST 40 STREET"}, "type": "Feature"}], "properties": {"square footage": "3,567,186"}, "type": "FeatureCollection"}