{"features": [{"geometry": {"coordinates": [-73.86140292912916, 40.83408692707387], "type": "Point"}, "properties": {"address": "11 HUGH J GRANT CIRCLE"}, "type": "Feature"}, {"geometry": {"coordinates": [-73.85893408031387, 40.836109533214554], "type": "Point"}, "properties": {"address": "62 PARKCHESTER ROAD"}, "type": "Feature"}, {"geometry": {"coordinates": [-73.86199536491439, 40.83767497893842], "type": "Point"}, "properties": {"address": "65 WOOD ROAD"}, "type": "Feature"}, {"geometry": {"coordinates": [-73.85652548241585, 40.838612485788516], "type": "Point"}, "properties": {"address": "14 METROPOLITAN OVAL"}, "type": "Feature"}], "properties": {"square footage": "7,126,785"}, "type": "FeatureCollection"}