{"features": [{"geometry": {"coordinates": [-73.8586622, 40.8385961], "type": "Point"}, "properties": {"address": "14 METROPOLITAN OVAL"}, "type": "Feature"}, {"geometry": {"coordinates": [-73.86129199999999, 40.8340891], "type": "Point"}, "properties": {"address": "11 HUGH J GRANT CIRCLE"}, "type": "Feature"}, {"geometry": {"coordinates": [-73.8595899, 40.8363245], "type": "Point"}, "properties": {"address": "62 PARKCHESTER ROAD"}, "type": "Feature"}, {"geometry": {"coordinates": [-73.86291469999999, 40.8401669], "type": "Point"}, "properties": {"address": "65 WOOD ROAD"}, "type": "Feature"}], "properties": {"square footage": "3,681,037"}, "type": "FeatureCollection"}