{"features": [{"geometry": {"coordinates": [-73.98159749999999, 40.731856], "type": "Point"}, "properties": {"address": "240 1 AVENUE"}, "type": "Feature"}], "properties": {"square footage": "8,942,176"}, "type": "FeatureCollection"}