{"features": [{"geometry": {"coordinates": [-73.79454494581657, 40.721878156130984], "type": "Point"}, "properties": {"address": "8150A UTOPIA PARKWAY"}, "type": "Feature"}], "properties": {"square footage": "4,687,440"}, "type": "FeatureCollection"}