{"features": [{"geometry": {"coordinates": [-73.7939232, 40.731705], "type": "Point"}, "properties": {"address": "8150A UTOPIA PARKWAY"}, "type": "Feature"}], "properties": {"square footage": "4,687,440"}, "type": "FeatureCollection"}