{"features": [{"geometry": {"coordinates": [-73.84638679999999, 40.7559005], "type": "Point"}, "properties": {"address": "123-01 ROOSEVELT AVENUE"}, "type": "Feature"}], "properties": {"total value": "1,360,162,000"}, "type": "FeatureCollection"}