{"features": [{"geometry": {"coordinates": [-73.97789635675532, 40.731723636068025], "type": "Point"}, "properties": {"address": "240 1 AVENUE"}, "type": "Feature"}], "properties": {"total value": "1,360,162,000"}, "type": "FeatureCollection"}