{"features": [{"geometry": {"coordinates": [-73.84732554773176, 40.756184606719145], "type": "Point"}, "properties": {"address": "123-01 ROOSEVELT AVENUE"}, "type": "Feature"}], "properties": {"total value": "1,332,865,000"}, "type": "FeatureCollection"}